{
  "Delhi": {
    "condition": "Fog",
    "temperature_c": 15.3,
    "updated_at": "2025-08-16T11:31:12.400332Z"
  },
  "Mumbai": {
    "condition": "Light rain",
    "temperature_c": 26.1,
    "updated_at": "2025-08-16T11:31:13.033707Z"
  },
  "Bangalore": {
    "condition": "Partly cloudy",
    "temperature_c": 24.3,
    "updated_at": "2025-08-16T11:31:13.657150Z"
  },
  "Chennai": {
    "condition": "Mist",
    "temperature_c": 28.4,
    "updated_at": "2025-08-16T11:31:14.290559Z"
  },
  "Hyderabad": {
    "condition": "Mist",
    "temperature_c": 25.2,
    "updated_at": "2025-08-16T11:31:14.923873Z"
  },
  "Gurgaon": {
    "condition": "Moderate or heavy rain with thunder",
    "temperature_c": 32.3,
    "updated_at": "2025-08-16T11:31:15.548332Z"
  }
}