{
  "Delhi": {
    "condition": "Sunny",
    "temperature_c": 12.3,
    "updated_at": "2025-08-25T11:31:12.660753Z"
  },
  "Mumbai": {
    "condition": "Light rain shower",
    "temperature_c": 26.5,
    "updated_at": "2025-08-25T11:31:13.309959Z"
  },
  "Bangalore": {
    "condition": "Sunny",
    "temperature_c": 27.2,
    "updated_at": "2025-08-25T11:31:13.965479Z"
  },
  "Chennai": {
    "condition": "Partly cloudy",
    "temperature_c": 34.4,
    "updated_at": "2025-08-25T11:31:14.636481Z"
  },
  "Hyderabad": {
    "condition": "Partly cloudy",
    "temperature_c": 30.2,
    "updated_at": "2025-08-25T11:31:15.285766Z"
  },
  "Gurgaon": {
    "condition": "Mist",
    "temperature_c": 29.2,
    "updated_at": "2025-08-25T11:31:15.941393Z"
  }
}